brecup/__init__.py
brecup/main.py
brecup-0.0.5.dist-info/METADATA
brecup-0.0.5.dist-info/WHEEL
brecup-0.0.5.dist-info/entry_points.txt
brecup-0.0.5.dist-info/top_level.txt
brecup-0.0.5.dist-info/RECORD
