Metadata-Version: 2.1
Name: brecup
Version: 0.0.5
Summary: Simplify the BililiveRecorder → biliup-rs workflow.
Author-email: aquanjsw <zhdlcc@gmail.com>
Project-URL: homepage, https://github.com/aquanjsw/brecup
Classifier: Programming Language :: Python :: 3
Classifier: Operating System :: OS Independent
Requires-Python: >=3.12
Requires-Dist: pyyaml
Requires-Dist: loguru
